e2b_code_interpreter/__init__.py
e2b_code_interpreter/charts.py
e2b_code_interpreter/code_interpreter_async.py
e2b_code_interpreter/code_interpreter_sync.py
e2b_code_interpreter/constants.py
e2b_code_interpreter/exceptions.py
e2b_code_interpreter/models.py
cmsbx_code_interpreter-0.0.1.dist-info/LICENSE
cmsbx_code_interpreter-0.0.1.dist-info/METADATA
cmsbx_code_interpreter-0.0.1.dist-info/WHEEL
cmsbx_code_interpreter-0.0.1.dist-info/RECORD
