Metadata-Version: 2.1
Name: cmsbx-code-interpreter
Version: 0.0.1
Summary: cmsbx Code Interpreter - Stateful code execution
License: MIT
Author: cmsbx
Author-email: baboyzyh@163.com
Requires-Python: >=3.9,<4.0
Classifier: License :: OSI Approved :: MIT License
Classifier: Programming Language :: Python :: 3
Classifier: Programming Language :: Python :: 3.9
Classifier: Programming Language :: Python :: 3.10
Classifier: Programming Language :: Python :: 3.11
Classifier: Programming Language :: Python :: 3.12
Requires-Dist: attrs (>=21.3.0)
Requires-Dist: cmsbx (>=0.0.6,<0.0.7)
Requires-Dist: httpx (>=0.20.0,<1.0.0)
